py_simple_sharepoint/__init__.py
py_simple_sharepoint/test_it.py
py_simple_sharepoint-1.1.0.dist-info/WHEEL
py_simple_sharepoint-1.1.0.dist-info/METADATA
py_simple_sharepoint-1.1.0.dist-info/RECORD
