Metadata-Version: 2.3
Name: py-simple-sharepoint
Version: 1.1.0
Summary: A SharePoint file management tool for python programs.
Requires-Dist: cryptography>=45.0.6
Requires-Dist: requests>=2.32.5
Requires-Python: >=3.10
